/* Auto-generated by Tools/scripts/generate_opcode_h.py from Lib/opcode.py */
#ifndef Py_OPCODE2_H
#define Py_OPCODE2_H
#ifdef __cplusplus
extern "C" {
#endif


    /* Instruction opcodes for compiled code */
#define CLEAR_ACC                 1
#define FUNC_HEADER               2
#define METHOD_HEADER             3
#define COROGEN_HEADER            4
#define CFUNC_HEADER              6
#define FUNC_TPCALL_HEADER        7
#define NOP                       9
#define UNARY_POSITIVE           10
#define UNARY_NEGATIVE           11
#define UNARY_NOT                12
#define UNARY_NOT_FAST           13
#define UNARY_INVERT             15
#define BINARY_MATRIX_MULTIPLY   16
#define INPLACE_MATRIX_MULTIPLY  17
#define BINARY_POWER             19
#define BINARY_MULTIPLY          20
#define BINARY_MODULO            22
#define BINARY_ADD               23
#define BINARY_SUBTRACT          24
#define BINARY_SUBSCR            25
#define BINARY_FLOOR_DIVIDE      26
#define BINARY_TRUE_DIVIDE       27
#define INPLACE_FLOOR_DIVIDE     28
#define INPLACE_TRUE_DIVIDE      29
#define LOAD_EXC                 30
#define LOAD_INTRINSIC           34
#define CALL_INTRINSIC_1         35
#define CALL_INTRINSIC_N         36
#define WITH_EXCEPT_START        49
#define GET_AITER                50
#define GET_ANEXT                51
#define END_ASYNC_WITH           52
#define END_ASYNC_FOR            54
#define INPLACE_ADD              55
#define INPLACE_SUBTRACT         56
#define INPLACE_MULTIPLY         57
#define INPLACE_MODULO           59
#define STORE_SUBSCR             60
#define DELETE_SUBSCR            61
#define BINARY_LSHIFT            62
#define BINARY_RSHIFT            63
#define BINARY_AND               64
#define BINARY_XOR               65
#define BINARY_OR                66
#define INPLACE_POWER            67
#define GET_ITER                 68
#define GET_YIELD_FROM_ITER      69
#define PRINT_EXPR               70
#define LOAD_BUILD_CLASS         71
#define YIELD_FROM               72
#define GET_AWAITABLE            73
#define LOAD_ASSERTION_ERROR     74
#define INPLACE_LSHIFT           75
#define INPLACE_RSHIFT           76
#define INPLACE_AND              77
#define INPLACE_XOR              78
#define INPLACE_OR               79
#define LIST_TO_TUPLE            82
#define RETURN_VALUE             83
#define IMPORT_STAR              84
#define SETUP_ANNOTATIONS        85
#define YIELD_VALUE              86
#define POP_BLOCK                87
#define END_EXCEPT               89
#define STORE_NAME               90
#define DELETE_NAME              91
#define FOR_ITER                 93
#define UNPACK                   94
#define STORE_ATTR               95
#define DELETE_ATTR              96
#define STORE_GLOBAL             97
#define DELETE_GLOBAL            98
#define LOAD_CONST              100
#define LOAD_NAME               101
#define BUILD_TUPLE             102
#define BUILD_LIST              103
#define BUILD_SET               104
#define BUILD_MAP               105
#define LOAD_ATTR               106
#define COMPARE_OP              107
#define IMPORT_NAME             108
#define IMPORT_FROM             109
#define JUMP_IF_FALSE           111
#define JUMP_IF_TRUE            112
#define JUMP                    113
#define POP_JUMP_IF_FALSE       114
#define POP_JUMP_IF_TRUE        115
#define LOAD_GLOBAL             116
#define IS_OP                   117
#define CONTAINS_OP             118
#define JUMP_IF_NOT_EXC_MATCH   121
#define END_FINALLY             122
#define CALL_FINALLY            123
#define LOAD_FAST               124
#define STORE_FAST              125
#define DELETE_FAST             126
#define RAISE                   130
#define CALL_FUNCTION           131
#define MAKE_FUNCTION           132
#define BUILD_SLICE             133
#define LOAD_DEREF              136
#define STORE_DEREF             137
#define DELETE_DEREF            138
#define CALL_FUNCTION_EX        142
#define SETUP_WITH              143
#define EXTENDED_ARG            144
#define LIST_APPEND             145
#define SET_ADD                 146
#define MAP_ADD                 147
#define LOAD_CLASSDEREF         148
#define END_WITH                150
#define SETUP_ASYNC_WITH        154
#define BUILD_CONST_KEY_MAP     156
#define LOAD_METHOD             160
#define CALL_METHOD             161
#define LIST_EXTEND             162
#define SET_UPDATE              163
#define DICT_MERGE              164
#define DICT_UPDATE             165
#define CLEAR_FAST              168
#define COPY                    169
#define MOVE                    170

#define OP_SIZE_CLEAR_ACC                 4
#define OP_SIZE_FUNC_HEADER               4
#define OP_SIZE_METHOD_HEADER             4
#define OP_SIZE_COROGEN_HEADER            4
#define OP_SIZE_CFUNC_HEADER              4
#define OP_SIZE_FUNC_TPCALL_HEADER        4
#define OP_SIZE_NOP                       4
#define OP_SIZE_UNARY_POSITIVE            4
#define OP_SIZE_UNARY_NEGATIVE            4
#define OP_SIZE_UNARY_NOT                 4
#define OP_SIZE_UNARY_NOT_FAST            4
#define OP_SIZE_UNARY_INVERT              4
#define OP_SIZE_BINARY_MATRIX_MULTIPLY    4
#define OP_SIZE_INPLACE_MATRIX_MULTIPLY   4
#define OP_SIZE_BINARY_POWER              4
#define OP_SIZE_BINARY_MULTIPLY           4
#define OP_SIZE_BINARY_MODULO             4
#define OP_SIZE_BINARY_ADD                4
#define OP_SIZE_BINARY_SUBTRACT           4
#define OP_SIZE_BINARY_SUBSCR             4
#define OP_SIZE_BINARY_FLOOR_DIVIDE       4
#define OP_SIZE_BINARY_TRUE_DIVIDE        4
#define OP_SIZE_INPLACE_FLOOR_DIVIDE      4
#define OP_SIZE_INPLACE_TRUE_DIVIDE       4
#define OP_SIZE_LOAD_EXC                  4
#define OP_SIZE_LOAD_INTRINSIC            4
#define OP_SIZE_CALL_INTRINSIC_1          4
#define OP_SIZE_CALL_INTRINSIC_N          4
#define OP_SIZE_WITH_EXCEPT_START         4
#define OP_SIZE_GET_AITER                 4
#define OP_SIZE_GET_ANEXT                 4
#define OP_SIZE_END_ASYNC_WITH            4
#define OP_SIZE_END_ASYNC_FOR             4
#define OP_SIZE_INPLACE_ADD               4
#define OP_SIZE_INPLACE_SUBTRACT          4
#define OP_SIZE_INPLACE_MULTIPLY          4
#define OP_SIZE_INPLACE_MODULO            4
#define OP_SIZE_STORE_SUBSCR              4
#define OP_SIZE_DELETE_SUBSCR             4
#define OP_SIZE_BINARY_LSHIFT             4
#define OP_SIZE_BINARY_RSHIFT             4
#define OP_SIZE_BINARY_AND                4
#define OP_SIZE_BINARY_XOR                4
#define OP_SIZE_BINARY_OR                 4
#define OP_SIZE_INPLACE_POWER             4
#define OP_SIZE_GET_ITER                  4
#define OP_SIZE_GET_YIELD_FROM_ITER       4
#define OP_SIZE_PRINT_EXPR                4
#define OP_SIZE_LOAD_BUILD_CLASS          4
#define OP_SIZE_YIELD_FROM                4
#define OP_SIZE_GET_AWAITABLE             4
#define OP_SIZE_LOAD_ASSERTION_ERROR      4
#define OP_SIZE_INPLACE_LSHIFT            4
#define OP_SIZE_INPLACE_RSHIFT            4
#define OP_SIZE_INPLACE_AND               4
#define OP_SIZE_INPLACE_XOR               4
#define OP_SIZE_INPLACE_OR                4
#define OP_SIZE_LIST_TO_TUPLE             4
#define OP_SIZE_RETURN_VALUE              4
#define OP_SIZE_IMPORT_STAR               4
#define OP_SIZE_SETUP_ANNOTATIONS         4
#define OP_SIZE_YIELD_VALUE               4
#define OP_SIZE_POP_BLOCK                 4
#define OP_SIZE_END_EXCEPT                4
#define OP_SIZE_STORE_NAME                4
#define OP_SIZE_DELETE_NAME               4
#define OP_SIZE_FOR_ITER                  4
#define OP_SIZE_UNPACK                    4
#define OP_SIZE_STORE_ATTR                4
#define OP_SIZE_DELETE_ATTR               4
#define OP_SIZE_STORE_GLOBAL              4
#define OP_SIZE_DELETE_GLOBAL             4
#define OP_SIZE_LOAD_CONST                4
#define OP_SIZE_LOAD_NAME                 4
#define OP_SIZE_BUILD_TUPLE               4
#define OP_SIZE_BUILD_LIST                4
#define OP_SIZE_BUILD_SET                 4
#define OP_SIZE_BUILD_MAP                 4
#define OP_SIZE_LOAD_ATTR                 4
#define OP_SIZE_COMPARE_OP                4
#define OP_SIZE_IMPORT_NAME               4
#define OP_SIZE_IMPORT_FROM               4
#define OP_SIZE_JUMP_IF_FALSE             4
#define OP_SIZE_JUMP_IF_TRUE              4
#define OP_SIZE_JUMP                      4
#define OP_SIZE_POP_JUMP_IF_FALSE         4
#define OP_SIZE_POP_JUMP_IF_TRUE          4
#define OP_SIZE_LOAD_GLOBAL               4
#define OP_SIZE_IS_OP                     4
#define OP_SIZE_CONTAINS_OP               4
#define OP_SIZE_JUMP_IF_NOT_EXC_MATCH     4
#define OP_SIZE_END_FINALLY               4
#define OP_SIZE_CALL_FINALLY              4
#define OP_SIZE_LOAD_FAST                 4
#define OP_SIZE_STORE_FAST                4
#define OP_SIZE_DELETE_FAST               4
#define OP_SIZE_RAISE                     4
#define OP_SIZE_CALL_FUNCTION             4
#define OP_SIZE_MAKE_FUNCTION             4
#define OP_SIZE_BUILD_SLICE               4
#define OP_SIZE_LOAD_DEREF                4
#define OP_SIZE_STORE_DEREF               4
#define OP_SIZE_DELETE_DEREF              4
#define OP_SIZE_CALL_FUNCTION_EX          4
#define OP_SIZE_SETUP_WITH                4
#define OP_SIZE_EXTENDED_ARG              4
#define OP_SIZE_LIST_APPEND               4
#define OP_SIZE_SET_ADD                   4
#define OP_SIZE_MAP_ADD                   4
#define OP_SIZE_LOAD_CLASSDEREF           4
#define OP_SIZE_END_WITH                  4
#define OP_SIZE_SETUP_ASYNC_WITH          4
#define OP_SIZE_BUILD_CONST_KEY_MAP       4
#define OP_SIZE_LOAD_METHOD               4
#define OP_SIZE_CALL_METHOD               4
#define OP_SIZE_LIST_EXTEND               4
#define OP_SIZE_SET_UPDATE                4
#define OP_SIZE_DICT_MERGE                4
#define OP_SIZE_DICT_UPDATE               4
#define OP_SIZE_CLEAR_FAST                4
#define OP_SIZE_COPY                      4
#define OP_SIZE_MOVE                      4


#ifdef __cplusplus
}
#endif
#endif /* !Py_OPCODE2_H */
